synfintabgen/__init__.py
synfintabgen/__main__.py
synfintabgen/configuration_dataset_generator.py
synfintabgen/execute_from_command_line.py
synfintabgen/generator_annotation.py
synfintabgen/generator_dataset.py
synfintabgen/generator_document.py
synfintabgen/generator_image.py
synfintabgen/generator_table.py
synfintabgen/generator_theme.py
synfintabgen-1.0.1.post1.dist-info/METADATA
synfintabgen-1.0.1.post1.dist-info/WHEEL
synfintabgen-1.0.1.post1.dist-info/entry_points.txt
synfintabgen-1.0.1.post1.dist-info/top_level.txt
synfintabgen-1.0.1.post1.dist-info/RECORD
