Metadata-Version: 2.4
Name: synfintabgen
Version: 1.0.1.post1
Summary: A package for generating synthetic financial tables.
Author: Ethan Bradley
Author-email: ebradley24@qub.ac.uk
License: MIT
Project-URL: Homepage, https://ethanbradley.co.uk/research/synfintabs
Project-URL: Issues, https://github.com/ethanbradley/synfintabgen/issues
Project-URL: Source, https://github.com/ethanbradley/synfintabgen
Requires-Python: >=3.10
Requires-Dist: easyocr>=1.7.1
Requires-Dist: htmltree>=0.7.6
Requires-Dist: nanoid>=2.0.0
Requires-Dist: nltk>=3.9.1
Requires-Dist: selenium>=4.19.0
Requires-Dist: tqdm>=4.66.2
